[
{
"Код": "00-00001866",
"Наименование": "Сторонние заказы"
},
{
"Код": "00-00002076",
"Наименование": "Разработки"
},
{
"Код": "00-00002077",
"Наименование": "Расходные материалы"
},
{
"Код": "ФР-00000367",
"Наименование": "Услуги"
},
{
"Код": "00-00000674",
"Наименование": "Хозтовары"
},
{
"Код": "00-00000736",
"Наименование": "Станки и оборудование, инструменты"
},
{
"Код": "00-00000188",
"Наименование": "Нелеквид/архив"
},
{
"Код": "00-00000189",
"Наименование": "Материалы и комплектующие"
},
{
"Код": "00-00000190",
"Наименование": "Полуфабрикаты"
},
{
"Код": "00-00000191",
"Наименование": "Готовая продукция"
}
]
